quizstarr/__init__.py
quizstarr/__main__.py
quizstarr/quizstarr.py
quizstarr-1.0.1.dist-info/LICENSE.txt
quizstarr-1.0.1.dist-info/METADATA
quizstarr-1.0.1.dist-info/WHEEL
quizstarr-1.0.1.dist-info/entry_points.txt
quizstarr-1.0.1.dist-info/top_level.txt
quizstarr-1.0.1.dist-info/RECORD
