Metadata-Version: 2.1
Name: quizstarr
Version: 1.0.1
Summary: A package that displays questions
Home-page: UNKNOWN
Author: Samuel .O. Bamgbose
Author-email: bsaintdesigns@gmail.com
License: UNKNOWN
Platform: UNKNOWN
Classifier: Programming Language :: Python :: 3.8
Classifier: License :: OSI Approved :: MIT License
Classifier: Operating System :: OS Independent
Requires-Python: >= 3.6
Requires-Dist: requests
